domain_shared_contacts_client/__init__.py
domain_shared_contacts_client/cli.py
domain_shared_contacts_client/contacts_helper.py
domain_shared_contacts_client/domain_shared_contacts_client.py
domain_shared_contacts_client-0.1.0.dist-info/top_level.txt
domain_shared_contacts_client-0.1.0.dist-info/entry_points.txt
domain_shared_contacts_client-0.1.0.dist-info/METADATA
domain_shared_contacts_client-0.1.0.dist-info/DESCRIPTION.rst
domain_shared_contacts_client-0.1.0.dist-info/metadata.json
domain_shared_contacts_client-0.1.0.dist-info/WHEEL
domain_shared_contacts_client-0.1.0.dist-info/RECORD
