Metadata-Version: 2.0
Name: domain-shared-contacts-client
Version: 0.1.0
Summary: A Python client to CRUD Google Domain Shared Contacts
Home-page: https://github.com/rjoyal/domain_shared_contacts_client
Author: Robert Joyal
Author-email: rjoyal@gmail.com
License: MIT license
Keywords: domain_shared_contacts_client
Platform: UNKNOWN
Classifier: Development Status :: 2 - Pre-Alpha
Classifier: Intended Audience :: Developers
Classifier: License :: OSI Approved :: MIT License
Classifier: Natural Language :: English
Classifier: Programming Language :: Python :: 2
Classifier: Programming Language :: Python :: 2.6
Classifier: Programming Language :: Python :: 2.7
Classifier: Programming Language :: Python :: 3
Classifier: Programming Language :: Python :: 3.3
Classifier: Programming Language :: Python :: 3.4
Classifier: Programming Language :: Python :: 3.5
Requires-Dist: Click (>=6.0)
Requires-Dist: gdata
Requires-Dist: oauth2client
